pysonar_scanner/__init__.py
pysonar_scanner/__main__.py
pysonar_scanner/api.py
pysonar_scanner/app_logging.py
pysonar_scanner/cache.py
pysonar_scanner/configuration/__init__.py
pysonar_scanner/configuration/cli.py
pysonar_scanner/configuration/configuration_loader.py
pysonar_scanner/configuration/coveragerc_loader.py
pysonar_scanner/configuration/dynamic_defaults_loader.py
pysonar_scanner/configuration/environment_variables.py
pysonar_scanner/configuration/properties.py
pysonar_scanner/configuration/pyproject_toml.py
pysonar_scanner/configuration/sonar_project_properties.py
pysonar_scanner/exceptions.py
pysonar_scanner/jre.py
pysonar_scanner/scannerengine.py
pysonar_scanner/utils.py
pysonar-1.2.0.2419.dist-info/LICENSE
pysonar-1.2.0.2419.dist-info/METADATA
pysonar-1.2.0.2419.dist-info/WHEEL
pysonar-1.2.0.2419.dist-info/entry_points.txt
pysonar-1.2.0.2419.dist-info/RECORD
